LICENSE.txt
MANIFEST.in
README.rst
config.example.ini
kanedama.py
setup.py
Kanedama.egg-info/PKG-INFO
Kanedama.egg-info/SOURCES.txt
Kanedama.egg-info/dependency_links.txt
Kanedama.egg-info/requires.txt
Kanedama.egg-info/top_level.txt